{
  "data": "[\n  {\n    \"title\": \"School of Arts\",\n    \"text\": \"-2.6034753,51.4575797\",\n    \"children\": [\n      {\n        \"title\": \"Anthropology and Archaeology\",\n        \"text\": \"Test Edit\",\n        \"children\": [],\n        \"id\": \"kqutatjbf\"\n      },\n      {\n        \"title\": \"Film and Television\",\n        \"text\": \"\",\n        \"children\": [],\n        \"id\": \"gvsyf6mz5\"\n      },\n      {\n        \"title\": \"Music\",\n        \"text\": \"\",\n        \"children\": [],\n        \"id\": \"dkpuhc1u7\"\n      },\n      {\n        \"title\": \"Philosophy\",\n        \"text\": \"\",\n        \"children\": [],\n        \"id\": \"53wt2qe5m\"\n      },\n      {\n        \"title\": \"Theatre\",\n        \"text\": \"\",\n        \"children\": [],\n        \"id\": \"3fpmi73wq\"\n      },\n      {\n        \"title\": \"Liberal Arts\",\n        \"text\": \"\",\n        \"children\": [\n          {\n            \"title\": \"The Public Role of Humanities\",\n            \"text\": \"\",\n            \"children\": [],\n            \"id\": \"c9gecpckp\"\n          }\n        ],\n        \"id\": \"462z081xp\"\n      }\n    ],\n    \"id\": \"1ec8xh3js\"\n  },\n  {\n    \"title\": \"School of Humanities\",\n    \"text\": \"-2.6064835,51.4608241\",\n    \"children\": [\n      {\n        \"title\": \"History\",\n        \"text\": \"\",\n        \"children\": [\n          {\n            \"title\": \"Classics and Ancient History\",\n            \"text\": \"\",\n            \"children\": [\n              {\n                \"title\": \"Applied Classics\",\n                \"text\": \"This module is aimed to develop students project management skills by challenging them to find a way to introduce an element of classics to the wider public.\\n This could be anything from an exhibition to an academic publication.\\n\",\n                \"children\": [\n                  {\n                    \"title\": \"Assessment\",\n                    \"text\": \"\",\n                    \"children\": [\n                      {\n                        \"title\": \"Formative\",\n                        \"text\": \"This is a three part assessment that has real world relevance and the assessment is integrated seamlessly into the task. \\n\\n It also requires students to collaborate and consider multiple stakeholders and perspectives. \\n\\n - Group minutes, budget, action plan and funding bids \\n - Individual student work logs and the preparation of a CV \\n - Project display \\n\\n\",\n                        \"children\": [],\n                        \"id\": \"cghygq6r0\"\n                      },\n                      {\n                        \"title\": \"Summative\",\n                        \"text\": \"Students are required to write a 3000 word reflective essay which not only asks students to reflect on the success of their own projects, but also the role for classics in the wider community.\",\n                        \"children\": [],\n                        \"id\": \"ezr2qtuje\"\n                      }\n                    ],\n                    \"id\": \"xbxij7zoh\"\n                  },\n                  {\n                    \"title\": \"Learning\",\n                    \"text\": \"Aside from the summative essay, students are required to work in groups to produce a polished end product. Sessions include training sessions from Careers, RED and more, demonstrating a variety of perspectives and developing a range of skills.\",\n                    \"children\": [],\n                    \"id\": \"tlxbvat0x\"\n                  }\n                ],\n                \"id\": \"tll5gh4pk\"\n              }\n            ],\n            \"id\": \"y4nhhy3hs\"\n          }\n        ],\n        \"id\": \"ezl9y8hqj\"\n      },\n      {\n        \"title\": \"English\",\n        \"text\": \"\",\n        \"children\": [\n          {\n            \"title\": \"Creative Non-Fiction\",\n            \"text\": \"\",\n            \"children\": [],\n            \"id\": \"ddnu65czv\"\n          },\n          {\n            \"title\": \"History of Art\",\n            \"text\": \"\",\n            \"children\": [],\n            \"id\": \"53k889gz7\"\n          },\n          {\n            \"title\": \"Religion and Theology\",\n            \"text\": \"\",\n            \"children\": [],\n            \"id\": \"yxehyde8n\"\n          }\n        ],\n        \"id\": \"0hauu4baz\"\n      }\n    ],\n    \"id\": \"6j5u0scpr\"\n  },\n  {\n    \"title\": \"School of Modern Languages\",\n    \"text\": \"-2.6038873,51.4600344\",\n    \"children\": [\n      {\n        \"title\": \"French\",\n        \"text\": \"\",\n        \"children\": [],\n        \"id\": \"w19wjeudp\"\n      },\n      {\n        \"title\": \"German\",\n        \"text\": \"\",\n        \"children\": [],\n        \"id\": \"ikxxjqk7i\"\n      },\n      {\n        \"title\": \"Hispanic, Portuguese and Latin American Studies\",\n        \"text\": \"\",\n        \"children\": [],\n        \"id\": \"to3f07ycu\"\n      },\n      {\n        \"title\": \"Italian\",\n        \"text\": \"\",\n        \"children\": [],\n        \"id\": \"zlsgridwc\"\n      },\n      {\n        \"title\": \"Russian\",\n        \"text\": \"\",\n        \"children\": [],\n        \"id\": \"dsddtkn01\"\n      }\n    ],\n    \"id\": \"se9q3jf1q\"\n  },\n  {\n    \"title\": \"Centre for Academic Language and Development\",\n    \"text\": \"-2.613346,51.4566\",\n    \"children\": [],\n    \"id\": \"zsh0o8xd3\"\n  },\n  {\n    \"title\": \"Engineering (CAME)\",\n    \"text\": \"-2.6020703,51.4566198\",\n    \"children\": [\n      {\n        \"title\": \"Aerospace Engineering\",\n        \"text\": \"\",\n        \"children\": [],\n        \"id\": \"86z8ut83s\"\n      },\n      {\n        \"title\": \"Civil Engineering\",\n        \"text\": \"\",\n        \"children\": [\n          {\n            \"title\": \"Timber Engineering 4 'The Office'\",\n            \"text\": \"\",\n            \"children\": [\n              {\n                \"title\": \"Description\",\n                \"text\": \"\",\n                \"children\": [],\n                \"id\": \"gielvfw5h\"\n              },\n              {\n                \"title\": \"Assessment\",\n                \"text\": \"\",\n                \"children\": [],\n                \"id\": \"ybepweiua\"\n              },\n              {\n                \"title\": \"Learning\",\n                \"text\": \"\",\n                \"children\": [],\n                \"id\": \"iw3fx58p9\"\n              }\n            ],\n            \"id\": \"uc857mgmo\"\n          }\n        ],\n        \"id\": \"p9pmse6v6\"\n      },\n      {\n        \"title\": \"Mechanical Engineering\",\n        \"text\": \"\",\n        \"children\": [],\n        \"id\": \"lu1bydbdw\"\n      }\n    ],\n    \"id\": \"ngkv6wbrk\"\n  },\n  {\n    \"title\": \"Engineering (SCEEM)\",\n    \"text\": \"-2.603079,51.4559332\",\n    \"children\": [\n      {\n        \"title\": \"Computer Science\",\n        \"text\": \"\",\n        \"children\": [],\n        \"id\": \"cdwm63h0s\"\n      },\n      {\n        \"title\": \"Electrical and Electronic Engineering\",\n        \"text\": \"\",\n        \"children\": [],\n        \"id\": \"vuf19pyv2\"\n      },\n      {\n        \"title\": \"Engineering Mathematics\",\n        \"text\": \"\",\n        \"children\": [],\n        \"id\": \"73yunuzwt\"\n      }\n    ],\n    \"id\": \"4ufl0tuyv\"\n  },\n  {\n    \"title\": \"Life Sciences\",\n    \"text\": \"-2.6011191,51.459189\",\n    \"children\": [\n      {\n        \"title\": \"School of Biological Sciences\",\n        \"text\": \"\",\n        \"children\": [],\n        \"id\": \"k7u7h21bq\"\n      },\n      {\n        \"title\": \"School of Biochemistry\",\n        \"text\": \"\",\n        \"children\": [],\n        \"id\": \"uix75wqji\"\n      },\n      {\n        \"title\": \"School of Cellular and Molecular Medicine\",\n        \"text\": \"\",\n        \"children\": [],\n        \"id\": \"q1ibyyvas\"\n      },\n      {\n        \"title\": \"School of Physiology, Pharmacology and Neuroscience\",\n        \"text\": \"\",\n        \"children\": [],\n        \"id\": \"2m82mb9qo\"\n      },\n      {\n        \"title\": \"School of Psychological Science\",\n        \"text\": \"\",\n        \"children\": [],\n        \"id\": \"q10la0dsw\"\n      },\n      {\n        \"title\": \"Life Sciences Faculty Office\",\n        \"text\": \"\",\n        \"children\": [\n          {\n            \"title\": \"Biomedical Research Employability and Enterprise Skills\",\n            \"text\": \"\",\n            \"children\": [\n              {\n                \"title\": \"Description\",\n                \"text\": \"\",\n                \"children\": [],\n                \"id\": \"4k1y47eat\"\n              },\n              {\n                \"title\": \"Assessment\",\n                \"text\": \"\",\n                \"children\": [],\n                \"id\": \"klwt0vdac\"\n              },\n              {\n                \"title\": \"Learning\",\n                \"text\": \"\",\n                \"children\": [],\n                \"id\": \"5onenw7hb\"\n              }\n            ],\n            \"id\": \"g6wk21dwa\"\n          }\n        ],\n        \"id\": \"r55xms5xb\"\n      }\n    ],\n    \"id\": \"elf0rdjky\"\n  },\n  {\n    \"title\": \"School of Chemistry\",\n    \"text\": \"-2.6028562,51.456341\",\n    \"children\": [\n      {\n        \"title\": \"Introductory Practical Chemistry\",\n        \"text\": \"Link to unit page: <a href='https://www.bris.ac.uk/unit-programme-catalogue/UnitDetails.jsa?ayrCode=19%2F20&unitCode=CHEM10004'>CHEM10004</a>\",\n        \"children\": [\n          {\n            \"title\": \"Description\",\n            \"text\": \"\",\n            \"children\": [],\n            \"id\": \"m14y03upe\"\n          },\n          {\n            \"title\": \"Assessment\",\n            \"text\": \"\",\n            \"children\": [],\n            \"id\": \"0hw8itugi\"\n          },\n          {\n            \"title\": \"Learning\",\n            \"text\": \"\",\n            \"children\": [],\n            \"id\": \"7nclmafn2\"\n          }\n        ],\n        \"id\": \"aynegpch6\"\n      },\n      {\n        \"title\": \"Intermediate Practical and Analytical Chemistry\",\n        \"text\": \"\",\n        \"children\": [],\n        \"id\": \"xsgtwdrdb\"\n      },\n      {\n        \"title\": \"Advanced Practical Chemistry\",\n        \"text\": \"\",\n        \"children\": [],\n        \"id\": \"gu1x82mo1\"\n      }\n    ],\n    \"id\": \"kpwgc6103\"\n  },\n  {\n    \"title\": \"School of Oral and Dental Sciences\",\n    \"text\": \"-2.594979,51.458658\",\n    \"children\": [\n      {\n        \"title\": \"Clinical Skills\",\n        \"text\": \"\",\n        \"children\": [],\n        \"id\": \"4245shfbi\"\n      },\n      {\n        \"title\": \"Personal and Professional Development\",\n        \"text\": \"\",\n        \"children\": [],\n        \"id\": \"k99xsc6f6\"\n      },\n      {\n        \"title\": \"Clinical Practice\",\n        \"text\": \"\",\n        \"children\": [],\n        \"id\": \"wfib9hp9r\"\n      }\n    ],\n    \"id\": \"elspjqhvo\"\n  },\n  {\n    \"title\": \"Bristol Medical School\",\n    \"text\": \"-2.602678,51.459282\",\n    \"children\": [],\n    \"id\": \"2n0ar6493\"\n  },\n  {\n    \"title\": \"Bristol Veterinary School\",\n    \"text\": \"-2.7817805,51.3448398\",\n    \"children\": [\n      {\n        \"title\": \"Professional Veterinary Nursing\",\n        \"text\": \"\",\n        \"children\": [],\n        \"id\": \"32xoeuv9q\"\n      },\n      {\n        \"title\": \"Professional Studies\",\n        \"text\": \"\",\n        \"children\": [],\n        \"id\": \"3jadbk3s5\"\n      },\n      {\n        \"title\": \"Animal Management\",\n        \"text\": \"\",\n        \"children\": [],\n        \"id\": \"6rsptaesm\"\n      },\n      {\n        \"title\": \"Clinical Nursing Practice\",\n        \"text\": \"\",\n        \"children\": [],\n        \"id\": \"zzwe0rnks\"\n      },\n      {\n        \"title\": \"Clinical Skills\",\n        \"text\": \"\",\n        \"children\": [],\n        \"id\": \"nks1kdhsn\"\n      }\n    ],\n    \"id\": \"98s8kyxvx\"\n  },\n  {\n    \"title\": \"SPAIS\",\n    \"text\": \"-2.6066094,51.4596129\",\n    \"children\": [\n      {\n        \"title\": \"Contemporary Feminist Thought\",\n        \"text\": \"\",\n        \"children\": [\n          {\n            \"title\": \"Description\",\n            \"text\": \"This unit not only requires students to think about academic theorists conceptualize gender and sex, but also how that is relevant to politics, citizenship and democracy.\",\n            \"children\": [],\n            \"id\": \"ikk50me51\"\n          },\n          {\n            \"title\": \"Assessment\",\n            \"text\": \"\\n\\n - 25% - 'Feature Article' on a famous feminist. This can be a real or imagined publication and requires students to think about how the famous feminist would talk but also develop their own interview style, and how that would fit the tone of their publication. \\n - 75% - A briefing proposing a research programme to a 'think tank' that includes an action plan and budget. This demonstrates students using their skills to consider multiple stakeholders and how that could be relevant to the real world. \\n\\n\",\n            \"children\": [],\n            \"id\": \"dhjfagzgy\"\n          },\n          {\n            \"title\": \"Learning\",\n            \"text\": \"This module requires students to think about how feminist thought is relevant to the 'real-world' in issues such as maternity leave and pay and discrimination. They should acquire skills outside of the classroom such as budgeting and engaging non-academic writing.\",\n            \"children\": [],\n            \"id\": \"w8eluhue0\"\n          }\n        ],\n        \"id\": \"1fivavphd\"\n      },\n      {\n        \"title\": \"Gaston's Unit\",\n        \"text\": \"\",\n        \"children\": [],\n        \"id\": \"s51qw3bwu\"\n      }\n    ],\n    \"id\": \"d33eezkfq\"\n  },\n  {\n    \"title\": \"School of Education\",\n    \"text\": \"51.455119, -2.604897\",\n    \"children\": [],\n    \"id\": \"jzqsebjwt\"\n  },\n  {\n    \"title\": \"School for Economics Finance and Management\",\n    \"text\": \"51.459994, -2.604883\",\n    \"children\": [],\n    \"id\": \"p4axfqpyt\"\n  },\n  {\n    \"title\": \"University of Bristol Law School\",\n    \"text\": \"-2.604476,51.456456\",\n    \"children\": [],\n    \"id\": \"4o26a5bkq\"\n  },\n  {\n    \"title\": \"Richmond Building\",\n    \"text\": \"-2.6150709,51.4568702\",\n    \"children\": [\n      {\n        \"title\": \"Bristol Hub\",\n        \"text\": \"\",\n        \"children\": [\n          {\n            \"title\": \"Social Impact Voluntary Scheme\",\n            \"text\": \"\",\n            \"children\": [],\n            \"id\": \"o6ai01iqm\"\n          },\n          {\n            \"title\": \"Social Innovation Project\",\n            \"text\": \"\",\n            \"children\": [],\n            \"id\": \"2l7xooy6m\"\n          }\n        ],\n        \"id\": \"n6q13onfr\"\n      },\n      {\n        \"title\": \"Bristol SU\",\n        \"text\": \"\",\n        \"children\": [\n          {\n            \"title\": \"Society Committee Members\",\n            \"text\": \"\\n\\n - President and Vice \\n - Treasurer \\n - Social Secretary \\n - Wellbeing Officer \\n\\n\",\n            \"children\": [\n              {\n                \"title\": \"Training Offered\",\n                \"text\": \"Student-Led Volunteering Opportunities\\n<a href='https://www.bristolsu.org.uk/skills-volunteering/student-led-projects'> Student Led Projects @ Bristol SU </a>\\n\",\n                \"children\": [],\n                \"id\": \"k6ksd8uic\"\n              }\n            ],\n            \"id\": \"2jvudw32c\"\n          }\n        ],\n        \"id\": \"r8yrzzupp\"\n      }\n    ],\n    \"id\": \"btdscm042\"\n  }\n]"
}